Metadata-Version: 1.0
Name: felipesilverioudacity
Version: 0.1
Summary: Gaussian distributions
Home-page: UNKNOWN
Author: Felipe Silverio
Author-email: felipe.dsrv@gmail.com
License: UNKNOWN
Platform: UNKNOWN
